torin/__init__.py
torin/core.py
torin-0.1.0.dist-info/licenses/LICENSE
torin-0.1.0.dist-info/METADATA
torin-0.1.0.dist-info/WHEEL
torin-0.1.0.dist-info/top_level.txt
torin-0.1.0.dist-info/RECORD
