Metadata-Version: 2.4
Name: torin
Version: 0.1.0
Summary: A lightweight logging and tracking utility
Home-page: https://github.com/torin-ai/torin
Author: Akshay Vegesna
Author-email: akshay.vegesna@gmail.com
Classifier: Programming Language :: Python :: 3
Classifier: License :: OSI Approved :: MIT License
Classifier: Operating System :: OS Independent
Requires-Python: >=3.6
License-File: LICENSE
Requires-Dist: requests>=2.25.0
Requires-Dist: orjson>=3.0.0
Dynamic: author
Dynamic: author-email
Dynamic: classifier
Dynamic: description
Dynamic: description-content-type
Dynamic: home-page
Dynamic: license-file
Dynamic: requires-dist
Dynamic: requires-python
Dynamic: summary
